{
  "required": true,
  "package": "srpmultiplier.mixin",
  "refmap": "mixins.srpmultiplier.refmap.json",
  "compatibilityLevel": "JAVA_8",
  "target": "@env(DEFAULT)",
  "minVersion": "0.8",
  "mixins": [
    "BlockEvolutionLureMixin",
    "BloodmoonEventHandlerMixin",
    "BloodmoonHandlerMixin",
    "ClientBloodmoonHandlerMixin",
    "EntityAIVenkrolSummonMixin",
    "EntityInfEndermanHeadMixin",
    "EntityInfEndermanMixin",
    "EntityPStationaryMixin",
    "LostCitiesForgeEventHandlersMixin",
    "ParasiteEventEntityMixin",
    "SRPClockMixin",
    "SRPDimensionMultiplierMixin",
    "SRPEventHandlerBusMixin",
    "SRPItemsMixin",
    "SRPSpawningMixin",
    "SRPWorldEntitySpawnerMixin",
    "WorldEntitySpawnerMixin",
    "playerphases.BlockEvolutionLureMixin",
    "playerphases.BlockInfestedRemainMixin",
    "playerphases.BlockInfestedRubbleMixin",
    "playerphases.BlockInfestedStainMixin",
    "playerphases.BlockInfestedTrunkMixin",
    "playerphases.EntityAINexusGrowMixin",
    "playerphases.EntityAIVenkrolSummonMixin",
    "playerphases.EntityMudoMixin",
    "playerphases.EntityPAdaptedMixin",
    "playerphases.EntityParasiteBaseMixin",
    "playerphases.ParasiteEventEntityMixin",
    "playerphases.ParasiteEventWorldMixin",
    "playerphases.SRPCommandEvolutionMixin",
    "playerphases.SRPEffectBaseMixin",
    "playerphases.SRPEventHandlerBusMixin",
    "playerphases.SRPSpawningDimensionMixin",
    "playerphases.SRPWorldDataMixin",
    "playerphases.SRPWorldEntitySpawnerMixin",
    "playerphases.TileEntityCanisterMixin",
    "playerphases.TileEntityDodMixin"
  ],
  "injectors": {
    "maxShiftBy": 10
  }
}